grina/__init__.py
grina/network.py
grina/node.py
grina-0.1.dist-info/METADATA
grina-0.1.dist-info/WHEEL
grina-0.1.dist-info/top_level.txt
grina-0.1.dist-info/RECORD
