Metadata-Version: 2.1
Name: grina
Version: 0.1
Summary: GRIps Network Analysis module.
Home-page: UNKNOWN
Author: tokudo
Author-email: okudo@nii.ac.jp
License: MIT
Keywords: network
Platform: UNKNOWN
Classifier: Programming Language :: Python :: 3.6
Requires-Dist: networkx (>=2.4)
